asv_rich_api_flask/EnrichedApp.py
asv_rich_api_flask/Errors.py
asv_rich_api_flask/Exceptions.py
asv_rich_api_flask/GenericBlueprint.py
asv_rich_api_flask/__init__.py
asv_rich_api_flask/support.py
asv_rich_api_flask-0.1.0a2.dist-info/LICENSE
asv_rich_api_flask-0.1.0a2.dist-info/METADATA
asv_rich_api_flask-0.1.0a2.dist-info/WHEEL
asv_rich_api_flask-0.1.0a2.dist-info/top_level.txt
asv_rich_api_flask-0.1.0a2.dist-info/RECORD
