Metadata-Version: 2.1
Name: asv-rich-api-flask
Version: 0.1.0a2
Summary: Base elements for an enriched API using flask
Author-email: Alejandro Sanchez Vega <m.a.sanchez.vega@gmail.com>
License: Apache License
Requires-Python: >=3.8
License-File: LICENSE
Requires-Dist: flask
Requires-Dist: d20-orm
